my_nric/__init__.py
my_nric/validator.py
my_nric_validator-0.0.3.dist-info/LICENSE
my_nric_validator-0.0.3.dist-info/METADATA
my_nric_validator-0.0.3.dist-info/WHEEL
my_nric_validator-0.0.3.dist-info/top_level.txt
my_nric_validator-0.0.3.dist-info/RECORD
